fordoc/__init__.py
fordoc-0.1.dist-info/METADATA
fordoc-0.1.dist-info/WHEEL
fordoc-0.1.dist-info/entry_points.txt
fordoc-0.1.dist-info/top_level.txt
fordoc-0.1.dist-info/RECORD
