Metadata-Version: 2.1
Name: fordoc
Version: 0.1
Summary: A simple package to print a meme message.
Home-page: https://github.com/yourusername/fordoc
Author: DocBot
Author-email: doc@twohackers.io
